{"author_metadata": {"username": "MrDatabase", "id": "72"}, "question_metadata": {"score": 37, "id": "110", "tags": "<usa><money><exchange><eu><eurozone>", "views": 47131}, "text": "I asked this question earlier and it would seem that the consensus is exchange some money before you go and take it with you, and then get the rest from ATM's while in the country.\n", "question": {"subtitle": "I'm traveling from the US to Europe in a few weeks.  When and what is the best method of exchanging dollars for Euros?  \nI imagine there's options like:\n\nat the airport when you arrive in Europe\nat a bank in the US before you leave\nat a bank in Europe upon arriving\n\n", "title": "What is the best method for exchanging dollars for Euros?"}, "user_metadata": {"username": "Darren Kopp", "reputation": 1124, "id": "10"}, "answer_metadata": {"accepted": 0, "length": 181, "score": 7, "upModVotes": 10, "downModVotes": 3, "id": "113"}, "id": "db614f4175663c9e77808c48348ffb1f"}
